Workbook
Name aporte_mes: APP!$C$10
Name patrimonio: APP!$C$13
Name qte_anos: APP!$C$11
Name Rendimento_carteira: APP!$F$11
Name salario: APP!$F$10
Name tx_mes: APP!$C$12

Sheet APP
B9: Investimento Mensal | E9: Configurações
B10: Quanto investir por mês? | C10: 500 | E10: Salário | F10: 5000
B11: Por quantos anos? | C11: 5 | E11: Rendimento da carteira | F11: 0.01079
B12: Taxa de Rendimento Mensal? | C12: =Rendimento_carteira -> 0.01079
B13: Patrimônio Acumulado? | C13: =FV(tx_mes,qte_anos*12,-aporte_mes) -> 41888.457 | E13: Sugestão de Investimento | F13: =F10*30% -> 1500
B14: Dividendos Mensais? | C14: =C13*tx_mes -> 451.97645
B17: Cenários | D17: Dividendos
A18: 2 | B18: Quanto renderia em 2 anos? | C18: =FV($C$12,$A18*12,-$C$10) -> 13613.814 | D18: =C18*Rendimento_carteira -> 146.89305
A19: 5 | B19: Quanto renderia em 5 anos? | C19: =FV($C$12,$A19*12,-$C$10) -> 41888.457 | D19: =C19*Rendimento_carteira -> 451.97645
A20: 10 | B20: Quanto renderia em 10 anos? | C20: =FV($C$12,$A20*12,-$C$10) -> 121642.11 | D20: =C20*Rendimento_carteira -> 1312.5183
A21: 20 | B21: Quanto renderia em 20 anos? | C21: =FV($C$12,$A21*12,-$C$10) -> 562599.2 | D21: =C21*Rendimento_carteira -> 6070.4454
A22: 30 | B22: Quanto renderia em 30 anos? | C22: =FV($C$12,$A22*12,-$C$10) -> 2161084.8 | D22: =C22*Rendimento_carteira -> 23318.105
B26: Perfil de Investimento | C26: Agressivo
B27: Valor a ser investido por mês | C27: =aporte_mes -> 500
B34: Tipos de FIIs | C34: Percentual | D34: Valor
B35: PAPEL | C35: =VLOOKUP($C$26&"-"&B35,tabela!A3:D22,4,) -> 0.4 | D35: =C35*$C$27 -> 200
B36: CONCRETO | C36: =VLOOKUP($C$26&"-"&B36,tabela!A4:D23,4,) -> 0.2 | D36: =C36*$C$27 -> 100
B37: HÍBRIDO | C37: =VLOOKUP($C$26&"-"&B37,tabela!A5:D24,4,) -> 0.1 | D37: =C37*$C$27 -> 50
B38: FOFs | C38: =VLOOKUP($C$26&"-"&B38,tabela!A6:D25,4,) -> 0.15 | D38: =C38*$C$27 -> 75
B39: DESENVOLVIMENTO | C39: =VLOOKUP($C$26&"-"&B39,tabela!A7:D26,4,) -> 0.075 | D39: =C39*$C$27 -> 37.5
B40: HOTELARIA | C40: =VLOOKUP($C$26&"-"&B40,tabela!A8:D27,4,) -> 0.075 | D40: =C40*$C$27 -> 37.5
B41: Total | C41: =SUM(C35:C40) -> 1 | D41: =SUM(D35:D40) -> 500

Sheet tabela
A2: CHAVE COMPOSTA | B2: Perfil | C2: Tipos de FIIs | D2: Percentual
A3: =B3&"-"&C3 -> Conservador-PAPEL | B3: Conservador | C3: PAPEL | D3: 0.25
A4: =B4&"-"&C4 -> Conservador-CONCRETO | B4: Conservador | C4: CONCRETO | D4: 0.5
A5: =B5&"-"&C5 -> Conservador-HÍBRIDO | B5: Conservador | C5: HÍBRIDO | D5: 0.1
A6: =B6&"-"&C6 -> Conservador-FOFs | B6: Conservador | C6: FOFs | D6: 0.15
A7: =B7&"-"&C7 -> Conservador-DESENVOLVIMENTO | B7: Conservador | C7: DESENVOLVIMENTO | D7: 0
A8: =B8&"-"&C8 -> Conservador-HOTELARIA | B8: Conservador | C8: HOTELARIA | D8: 0
A9: =B9&"-"&C9 -> -
A10: =B10&"-"&C10 -> Moderado-PAPEL | B10: Moderado | C10: PAPEL | D10: 0.3
A11: =B11&"-"&C11 -> Moderado-CONCRETO | B11: Moderado | C11: CONCRETO | D11: 0.35
A12: =B12&"-"&C12 -> Moderado-HÍBRIDO | B12: Moderado | C12: HÍBRIDO | D12: 0.125
A13: =B13&"-"&C13 -> Moderado-FOFs | B13: Moderado | C13: FOFs | D13: 0.125
A14: =B14&"-"&C14 -> Moderado-DESENVOLVIMENTO | B14: Moderado | C14: DESENVOLVIMENTO | D14: 0.05
A15: =B15&"-"&C15 -> Moderado-HOTELARIA | B15: Moderado | C15: HOTELARIA | D15: 0.05
A16: =B16&"-"&C16 -> -
A17: =B17&"-"&C17 -> Agressivo-PAPEL | B17: Agressivo | C17: PAPEL | D17: 0.4
A18: =B18&"-"&C18 -> Agressivo-CONCRETO | B18: Agressivo | C18: CONCRETO | D18: 0.2
A19: =B19&"-"&C19 -> Agressivo-HÍBRIDO | B19: Agressivo | C19: HÍBRIDO | D19: 0.1
A20: =B20&"-"&C20 -> Agressivo-FOFs | B20: Agressivo | C20: FOFs | D20: 0.15
A21: =B21&"-"&C21 -> Agressivo-DESENVOLVIMENTO | B21: Agressivo | C21: DESENVOLVIMENTO | D21: 0.075
A22: =B22&"-"&C22 -> Agressivo-HOTELARIA | B22: Agressivo | C22: HOTELARIA | D22: 0.075
